{
    "paikat": [
        {"place":"Koulu","roles":["Opettaja","Opiskelija","Rehtori","Siivooja","Vanhempi","Vierailija"]},
        {"place":"Kirjasto","roles":["Kirjastonhoitaja","Asiakas","Opiskelija","Turisti","Vieras","Kirjanmyyjä"]},
        {"place":"Puisto","roles":["Kävelijä","Pyöräilijä","Urheilija","Lemmikinomistaja","Puistonhoitaja","Valokuvaaja"]},
        {"place":"Kauppa","roles":["Kassatyöntekijä","Asiakas","Myyjä","Hyllyttäjä","Tavarantoimittaja","Vieras"]},
        {"place":"Uimahalli","roles":["Uimaopettaja","Pelastaja","Asiakas","Siivooja","Kuntosaliohjaaja","Vierailija"]},
        {"place":"Eläintarha","roles":["Eläintenhoitaja","Opas","Asiakas","Myyntityöntekijä","Turisti","Vieras"]},
        {"place":"Tiedekeskus","roles":["Tiedemies","Opas","Asiakas","Toimittaja","Näyttelynvalvoja","Vieras"]},
        {"place":"Jäähalli","roles":["Jääkiekkoilija","Valmentaja","Tuomari","Katsoja","Myyntityöntekijä","Jäävalvoja"]},
        {"place":"Leikkipuisto","roles":["Lapsi","Vanhempi","Leikkipuistonvalvoja","Jäätelönmyyjä","Turisti","Siivooja"]},
        {"place":"Kirpputori","roles":["Myyjä","Asiakas","Tori-isäntä","Lastenvaunujenvuokraaja","Kahvilatyöntekijä","Vieras"]},
        {"place":"Linnanmäki","roles":["Vieras","Työntekijä","Huvipuistonvalvoja","Jäätelönmyyjä","Laitteenoperaattori","Siivooja"]},
        {"place":"Kampuskartano","roles":["Opiskelija","Opettaja","Kirjastonhoitaja","Keittäjä","Siivooja","Vierailija"]},
        {"place":"Maatalousnäyttely","roles":["Maajussi","Eläintenhoitaja","Asiakas","Kahvilatyöntekijä","Näyttelynvalvoja","Vieras"]},
        {"place":"Lentokenttä","roles":["Lentokenttätyöntekijä","Matkustaja","Turisti","Kahvilatyöntekijä","Turvamies","Siivooja"]},
        {"place":"Rautatieasema","roles":["Lipunmyyjä","Matkustaja","Turisti","Kahvilatyöntekijä","Rautatietäjä","Siivooja"]},
        {"place":"Kirjailijakongressi","roles":["Kirjailija","Kustantaja","Opiskelija","Toimittaja","Kääntäjä","Vieras"]},
        {"place":"Käsityökeskus","roles":["Ohjaaja","Oppilas","Myyntityöntekijä","Asiakas","Taiteilija","Vierailija"]},
        {"place":"Tanssikoulu","roles":["Tanssinopettaja","Oppilas","Vanhempi","Siivooja","Musiikkivalvoja","Vieras"]},
        {"place":"Teatteri","roles":["Näyttelijä","Ohjaaja","Katsomo","Valo- ja ääniteknikko","Lipunmyyjä","Siivooja"]},
        {"place":"Kuvataidenäyttely","roles":["Taiteilija","Kuraattori","Asiakas","Opas","Turisti","Vieras"]},
        {"place":"Lastenkirjastopäivä","roles":["Kertojamummo","Lapsi","Vanhempi","Kirjastonhoitaja","Käsityöohjaaja","Vieras"]},
        {"place":"Tietokonepaja","roles":["Ohjelmoija","Pelinkehittäjä","Opiskelija","Ohjaaja","Pelinkokeilija","Vieras"]},
        {"place":"Käsityöleiri","roles":["Ohjaaja","Oppilas","Vanhempi","Ruokatyöntekijä","Siivooja","Vierailija"]},
        {"place":"Luontoretki","roles":["Retkeilyopas","Opiskelija","Luonnonsuojelija","Kartanlukija","Kokki","Vieras"]},
        {"place":"Kodinmetsästys","roles":["Järjestäjä","Osallistuja","Vinkkienantaja","Kartanpitäjä","Valvoja","Vieras"]},
        {"place":"Lumilinnanrakennuskilpailu","roles":["Kilpailija","Tuomari","Katsoja","Kuumajuomanmyyjä","Valvoja","Vieras"]},
        {"place":"Koiranäyttely","roles":["Koiranomistaja","Tuomari","Katsoja","Myyntityöntekijä","Eläinlääkäri","Vieras"]},
        {"place":"Kevätmarkkinat","roles":["Myyjä","Asiakas","Musiikkiesiintyjä","Kahvilatyöntekijä","Markkinavirkailija","Vieras"]},
        {"place":"Kesäteatteri","roles":["Näyttelijä","Ohjaaja","Yleisö","Valaistusteknikko","Lipunmyyjä","Siivooja"]},
        {"place":"Lukupiiri","roles":["Kirjailija","Lukija","Kustantaja","Toimittaja","Kirjakaupan edustaja","Vieras"]},
        {"place":"Koodauskerho","roles":["Ohjaaja","Oppilas","Vanhempi","Pelinkehittäjä","Kilpailija","Vieras"]},
        {"place":"Lautapelikahvila","roles":["Peliohjaaja","Asiakas","Pelinkehittäjä","Kahvilatyöntekijä","Pelivalvoja","Vieras"]},
        {"place":"Lempieläinkerho","roles":["Ohjaaja","Lapsi","Vanhempi","Eläintenhoitaja","Käsityöohjaaja","Vieras"]},
        {"place":"Piirustuskurssi","roles":["Taideopettaja","Oppilas","Vanhempi","Materiaalitoimittaja","Näyttelynvalvoja","Vieras"]},
        {"place":"Robottikerho","roles":["Ohjaaja","Oppilas","Robotinrakentaja","Kilpailija","Tuomari","Vieras"]},
        {"place":"Tiedekerho","roles":["Tiedemies","Oppilas","Koehenkilö","Demonstraattori","Vanhempi","Vieras"]}
    ]
}